pyrotd/__init__.py
tests/__init__.py
tests/test_osc_resp.py
tests/test_spectra.py
pyRotd-0.6.1.dist-info/AUTHORS.rst
pyRotd-0.6.1.dist-info/LICENSE
pyRotd-0.6.1.dist-info/LICENSE.txt
pyRotd-0.6.1.dist-info/METADATA
pyRotd-0.6.1.dist-info/WHEEL
pyRotd-0.6.1.dist-info/top_level.txt
pyRotd-0.6.1.dist-info/RECORD
