Metadata-Version: 2.1
Name: pyRotd
Version: 0.6.1
Summary: Rotated response spectrum calculation implemented in Python.
Home-page: http://github.com/arkottke/pyrotd
Author: Albert Kottke
Author-email: albert.kottke@gmail.com
License: MIT
Keywords: response spectrum,earthquake ground motion
Classifier: Development Status :: 4 - Beta
Classifier: License :: OSI Approved :: MIT License
Classifier: Natural Language :: English
Classifier: Operating System :: OS Independent
Classifier: Programming Language :: Python
Classifier: Topic :: Scientific/Engineering
Classifier: Intended Audience :: Science/Research
License-File: LICENSE
License-File: LICENSE.txt
License-File: AUTHORS.rst
Requires-Dist: numpy
Requires-Dist: setuptools
